<worksheet xmlns="http://schemas.openxmlformats.org/spreadsheetml/2006/main"><sheetPr><outlinePr summaryBelow="1" summaryRight="1"/><pageSetUpPr/></sheetPr><dimension ref="A1:L31"/><sheetViews><sheetView showGridLines="0" workbookViewId="0"><pane ySplit="2" topLeftCell="A3" activePane="bottomLeft" state="frozen"/><selection pane="bottomLeft" activeCell="A1" sqref="A1"/></sheetView></sheetViews><sheetFormatPr baseColWidth="8" defaultRowHeight="15"/><cols><col width="6" customWidth="1" min="1" max="1"/><col width="6" customWidth="1" min="2" max="2"/><col width="6" customWidth="1" min="3" max="3"/><col width="38" customWidth="1" min="4" max="4"/><col width="14" customWidth="1" min="5" max="5"/><col width="14" customWidth="1" min="6" max="6"/><col width="16" customWidth="1" min="7" max="7"/><col width="12" customWidth="1" min="8" max="8"/><col width="12" customWidth="1" min="9" max="9"/><col width="24" customWidth="1" min="10" max="10"/><col width="14" customWidth="1" min="11" max="11"/><col width="9" customWidth="1" min="12" max="12"/></cols><sheetData><row r="1" ht="26" customHeight="1"><c r="A1" s="26" t="inlineStr"><is><t>SUNPRO ST GEORGE &#8211; PROCUREMENT SUMMARY | RODRIGUEZ RESIDENCE</t></is></c></row><row r="2" ht="16" customHeight="1"><c r="A2" s="2" t="inlineStr"><is><t>Sunpro St George | 3781 S River Rd St George UT 84790 | 435-634-2220 | Kevin Gill 435-669-5347 | TruStile Acct Mgr: Paris Raymond | Existing Quote SQAQGI000175-1 (08/29/2025) &#8211; TMF2200 basis &#8211; UPDATE REQUIRED</t></is></c></row><row r="4" ht="20" customHeight="1"><c r="A4" s="27" t="inlineStr"><is><t>UPDATED DOOR TYPE SUMMARY &#8211; BY MODEL</t></is></c></row><row r="5" ht="28" customHeight="1"><c r="A5" s="3" t="inlineStr"><is><t>Plan Tag</t></is></c><c r="B5" s="3" t="inlineStr"><is><t>TruStile Model</t></is></c><c r="C5" s="3" t="inlineStr"><is><t>Style</t></is></c><c r="D5" s="3" t="inlineStr"><is><t>Material</t></is></c><c r="E5" s="3" t="inlineStr"><is><t>Finish</t></is></c><c r="F5" s="3" t="inlineStr"><is><t>Thickness</t></is></c><c r="G5" s="3" t="inlineStr"><is><t>Height</t></is></c><c r="H5" s="3" t="inlineStr"><is><t>Sticking</t></is></c><c r="I5" s="3" t="inlineStr"><is><t>Glass</t></is></c><c r="J5" s="3" t="inlineStr"><is><t>Fire Rating</t></is></c><c r="K5" s="3" t="inlineStr"><is><t>Design Code</t></is></c><c r="L5" s="3" t="inlineStr"><is><t>Est. Qty</t></is></c></row><row r="6" ht="20" customHeight="1"><c r="A6" s="28" t="inlineStr"><is><t>DOOR 1</t></is></c><c r="B6" s="28" t="inlineStr"><is><t>FL100</t></is></c><c r="C6" s="29" t="inlineStr"><is><t>Full-Lite Glass</t></is></c><c r="D6" s="29" t="inlineStr"><is><t>MDF</t></is></c><c r="E6" s="29" t="inlineStr"><is><t>Bright Gray</t></is></c><c r="F6" s="29" t="inlineStr"><is><t>1-3/4"</t></is></c><c r="G6" s="29" t="inlineStr"><is><t>8'-0"</t></is></c><c r="H6" s="29" t="inlineStr"><is><t>One Step (OS)</t></is></c><c r="I6" s="29" t="inlineStr"><is><t>Clear</t></is></c><c r="J6" s="29" t="inlineStr"><is><t>Non-Rated</t></is></c><c r="K6" s="29" t="inlineStr"><is><t>C8ZT9dSob</t></is></c><c r="L6" s="28" t="n"><v>2</v></c></row><row r="7" ht="20" customHeight="1"><c r="A7" s="30" t="inlineStr"><is><t>DOOR 2</t></is></c><c r="B7" s="30" t="inlineStr"><is><t>TMF1000</t></is></c><c r="C7" s="31" t="inlineStr"><is><t>Flush</t></is></c><c r="D7" s="31" t="inlineStr"><is><t>MDF</t></is></c><c r="E7" s="31" t="inlineStr"><is><t>Off-White</t></is></c><c r="F7" s="31" t="inlineStr"><is><t>1-3/4"</t></is></c><c r="G7" s="31" t="inlineStr"><is><t>8'-0"</t></is></c><c r="H7" s="31" t="inlineStr"><is><t>N/A (Flush)</t></is></c><c r="I7" s="31" t="inlineStr"><is><t>None</t></is></c><c r="J7" s="31" t="inlineStr"><is><t>Non-Rated</t></is></c><c r="K7" s="31" t="inlineStr"><is><t>1tRmHbBwT</t></is></c><c r="L7" s="30" t="n"><v>11</v></c></row><row r="8" ht="20" customHeight="1"><c r="A8" s="32" t="inlineStr"><is><t>DOOR 3</t></is></c><c r="B8" s="32" t="inlineStr"><is><t>TS1000</t></is></c><c r="C8" s="33" t="inlineStr"><is><t>Shaker Panel</t></is></c><c r="D8" s="33" t="inlineStr"><is><t>MDF</t></is></c><c r="E8" s="33" t="inlineStr"><is><t>Bright Gray</t></is></c><c r="F8" s="33" t="inlineStr"><is><t>1-3/4"</t></is></c><c r="G8" s="33" t="inlineStr"><is><t>8'-0"</t></is></c><c r="H8" s="33" t="inlineStr"><is><t>One Step (OS)</t></is></c><c r="I8" s="33" t="inlineStr"><is><t>None</t></is></c><c r="J8" s="33" t="inlineStr"><is><t>Non-Rated</t></is></c><c r="K8" s="33" t="inlineStr"><is><t>Au31tRnqMY</t></is></c><c r="L8" s="32" t="n"><v>7</v></c></row><row r="9" ht="20" customHeight="1"><c r="A9" s="34" t="inlineStr"><is><t>DOOR 4</t></is></c><c r="B9" s="34" t="inlineStr"><is><t>TMF1000</t></is></c><c r="C9" s="35" t="inlineStr"><is><t>Flush Ext.</t></is></c><c r="D9" s="35" t="inlineStr"><is><t>MDF</t></is></c><c r="E9" s="35" t="inlineStr"><is><t>Bright Gray</t></is></c><c r="F9" s="35" t="inlineStr"><is><t>1-3/4"</t></is></c><c r="G9" s="35" t="inlineStr"><is><t>8'-0"</t></is></c><c r="H9" s="35" t="inlineStr"><is><t>N/A (Flush)</t></is></c><c r="I9" s="35" t="inlineStr"><is><t>None</t></is></c><c r="J9" s="35" t="inlineStr"><is><t>20-Min FR (garage)</t></is></c><c r="K9" s="35" t="inlineStr"><is><t>EICnMYsYv</t></is></c><c r="L9" s="34" t="n"><v>4</v></c></row><row r="10" ht="20" customHeight="1"><c r="A10" s="36" t="inlineStr"><is><t>SPECIAL</t></is></c><c r="B10" s="36" t="inlineStr"><is><t>N/A</t></is></c><c r="C10" s="37" t="inlineStr"><is><t>Vault/Ballistic</t></is></c><c r="D10" s="37" t="inlineStr"><is><t>Steel</t></is></c><c r="E10" s="37" t="inlineStr"><is><t>N/A</t></is></c><c r="F10" s="37" t="inlineStr"><is><t>N/A</t></is></c><c r="G10" s="37" t="inlineStr"><is><t>TBD</t></is></c><c r="H10" s="37" t="inlineStr"><is><t>N/A</t></is></c><c r="I10" s="37" t="inlineStr"><is><t>N/A</t></is></c><c r="J10" s="37" t="inlineStr"><is><t>Ballistic</t></is></c><c r="K10" s="37" t="inlineStr"><is><t>N/A</t></is></c><c r="L10" s="36" t="n"><v>1</v></c></row><row r="13" ht="18" customHeight="1"><c r="A13" s="38" t="inlineStr"><is><t>EXISTING QUOTE SQAQGI000175-1 (TMF2200 Basis &#8211; DO NOT ORDER &#8211; UPDATE REQUIRED)</t></is></c></row><row r="14" ht="24" customHeight="1"><c r="A14" s="39" t="inlineStr"><is><t>Line</t></is></c><c r="B14" s="39" t="inlineStr"><is><t>Qty</t></is></c><c r="C14" s="39" t="inlineStr"><is><t>UOM</t></is></c><c r="D14" s="39" t="inlineStr"><is><t>Description</t></is></c><c r="E14" s="39" t="inlineStr"><is><t>Size</t></is></c><c r="F14" s="39" t="inlineStr"><is><t>Config</t></is></c><c r="G14" s="39" t="inlineStr"><is><t>Fire Rating</t></is></c><c r="H14" s="39" t="inlineStr"><is><t>Unit $</t></is></c><c r="I14" s="39" t="inlineStr"><is><t>Extended $</t></is></c><c r="J14" s="39" t="inlineStr"><is><t>Notes</t></is></c></row><row r="15" ht="22" customHeight="1"><c r="A15" s="40" t="n"><v>1</v></c><c r="B15" s="41" t="n"><v>4</v></c><c r="C15" s="41" t="inlineStr"><is><t>EA</t></is></c><c r="D15" s="42" t="inlineStr"><is><t>29-13/16" x 96" TMF2200 Swing Single, Prehung, Kerf, Bevel Lock RH, Prime, Wedge</t></is></c><c r="E15" s="41" t="inlineStr"><is><t>29-13/16" x 96"</t></is></c><c r="F15" s="41" t="inlineStr"><is><t>Single Swing</t></is></c><c r="G15" s="41" t="inlineStr"><is><t>Non-Rated</t></is></c><c r="H15" s="41" t="inlineStr"><is><t>$1,070.22</t></is></c><c r="I15" s="41" t="inlineStr"><is><t>$4,280.86</t></is></c><c r="J15" s="43" t="inlineStr"><is><t>&#9888;&#65039; Update &#8211; new door types</t></is></c></row><row r="16" ht="22" customHeight="1"><c r="A16" s="40" t="n"><v>2</v></c><c r="B16" s="41" t="n"><v>7</v></c><c r="C16" s="41" t="inlineStr"><is><t>EA</t></is></c><c r="D16" s="42" t="inlineStr"><is><t>35-13/16" x 96" TMF2200 Swing Single, Prehung, Kerf, Bevel Lock RH, Prime, Wedge</t></is></c><c r="E16" s="41" t="inlineStr"><is><t>35-13/16" x 96"</t></is></c><c r="F16" s="41" t="inlineStr"><is><t>Single Swing</t></is></c><c r="G16" s="41" t="inlineStr"><is><t>Non-Rated</t></is></c><c r="H16" s="41" t="inlineStr"><is><t>$1,088.26</t></is></c><c r="I16" s="41" t="inlineStr"><is><t>$7,617.83</t></is></c><c r="J16" s="43" t="inlineStr"><is><t>&#9888;&#65039; Update &#8211; new door types</t></is></c></row><row r="17" ht="22" customHeight="1"><c r="A17" s="40" t="n"><v>3</v></c><c r="B17" s="41" t="n"><v>8</v></c><c r="C17" s="41" t="inlineStr"><is><t>EA</t></is></c><c r="D17" s="42" t="inlineStr"><is><t>31-13/16" x 96" TMF2200 Slab Only, Single, Kerf, Bevel Lock RH, Prime, Wedge</t></is></c><c r="E17" s="41" t="inlineStr"><is><t>31-13/16" x 96"</t></is></c><c r="F17" s="41" t="inlineStr"><is><t>Slab Only</t></is></c><c r="G17" s="41" t="inlineStr"><is><t>Non-Rated</t></is></c><c r="H17" s="41" t="inlineStr"><is><t>$863.86</t></is></c><c r="I17" s="41" t="inlineStr"><is><t>$6,910.89</t></is></c><c r="J17" s="43" t="inlineStr"><is><t>&#9888;&#65039; Update &#8211; new door types</t></is></c></row><row r="18" ht="22" customHeight="1"><c r="A18" s="40" t="n"><v>4</v></c><c r="B18" s="41" t="n"><v>3</v></c><c r="C18" s="41" t="inlineStr"><is><t>EA</t></is></c><c r="D18" s="42" t="inlineStr"><is><t>35-13/16" x 96" TMF2200 Swing Single, Prehung, Kerf, 20-Min FR, Unknown Handing</t></is></c><c r="E18" s="41" t="inlineStr"><is><t>35-13/16" x 96"</t></is></c><c r="F18" s="41" t="inlineStr"><is><t>Single Swing</t></is></c><c r="G18" s="41" t="inlineStr"><is><t>20-Min FR</t></is></c><c r="H18" s="41" t="inlineStr"><is><t>$2,302.85</t></is></c><c r="I18" s="41" t="inlineStr"><is><t>$6,908.54</t></is></c><c r="J18" s="43" t="inlineStr"><is><t>&#9888;&#65039; DOOR 4; confirm handing</t></is></c></row><row r="19" ht="22" customHeight="1"><c r="A19" s="40" t="n"><v>5</v></c><c r="B19" s="41" t="n"><v>1</v></c><c r="C19" s="41" t="inlineStr"><is><t>EA</t></is></c><c r="D19" s="42" t="inlineStr"><is><t>35-13/16" x 96" per leaf TMF2200 Swing Pair, Prehung, Kerf, Bevel Meeting Stiles</t></is></c><c r="E19" s="41" t="inlineStr"><is><t>35-13/16" ea.</t></is></c><c r="F19" s="41" t="inlineStr"><is><t>Pair</t></is></c><c r="G19" s="41" t="inlineStr"><is><t>Non-Rated</t></is></c><c r="H19" s="41" t="inlineStr"><is><t>$2,196.92</t></is></c><c r="I19" s="41" t="inlineStr"><is><t>$2,196.92</t></is></c><c r="J19" s="43" t="inlineStr"><is><t>&#9888;&#65039; Update to DOOR 1 pair</t></is></c></row><row r="20" ht="22" customHeight="1"><c r="A20" s="40" t="n"><v>6</v></c><c r="B20" s="41" t="n"><v>1</v></c><c r="C20" s="41" t="inlineStr"><is><t>EA</t></is></c><c r="D20" s="42" t="inlineStr"><is><t>Manufacturer Freight for 24 Doors</t></is></c><c r="E20" s="41" t="inlineStr"><is><t>&#8212;</t></is></c><c r="F20" s="41" t="inlineStr"><is><t>&#8212;</t></is></c><c r="G20" s="41" t="inlineStr"><is><t>&#8212;</t></is></c><c r="H20" s="41" t="inlineStr"><is><t>$300.00</t></is></c><c r="I20" s="41" t="inlineStr"><is><t>$300.00</t></is></c><c r="J20" s="42" t="inlineStr"><is><t>Retain &#8211; re-quote for new order</t></is></c></row><row r="21" ht="20" customHeight="1"><c r="A21" s="44" t="inlineStr"><is><t>ORIGINAL QUOTE TOTAL &#8211; DO NOT ORDER</t></is></c><c r="I21" s="45" t="inlineStr"><is><t>$28,215.05</t></is></c></row><row r="23" ht="18" customHeight="1"><c r="A23" s="46" t="inlineStr"><is><t>ACTION ITEMS &#8211; REQUIRED BEFORE PLACING NEW ORDER WITH SUNPRO / TRUSTILE</t></is></c></row><row r="24" ht="26" customHeight="1"><c r="A24" s="47" t="inlineStr"><is><t>1</t></is></c><c r="B24" s="48" t="inlineStr"><is><t>Confirm all rough opening sizes from updated Revit plans before submitting new order</t></is></c></row><row r="25" ht="26" customHeight="1"><c r="A25" s="47" t="inlineStr"><is><t>2</t></is></c><c r="B25" s="48" t="inlineStr"><is><t>Request updated quote from Sunpro using new door types: FL100, TMF1000 Off-White, TS1000, TMF1000 Bright Gray &#8211; reference TruStile design codes on this sheet</t></is></c></row><row r="26" ht="26" customHeight="1"><c r="A26" s="47" t="inlineStr"><is><t>3</t></is></c><c r="B26" s="48" t="inlineStr"><is><t>Confirm handing (LH/RH) for every door &#8211; existing quote flags Unknown Handing on fire-rated door (Line 4)</t></is></c></row><row r="27" ht="26" customHeight="1"><c r="A27" s="47" t="inlineStr"><is><t>4</t></is></c><c r="B27" s="48" t="inlineStr"><is><t>Confirm primary suite entry config: pair vs. single leaf; confirm glass spec for FL100 (clear vs. obscure)</t></is></c></row><row r="28" ht="26" customHeight="1"><c r="A28" s="47" t="inlineStr"><is><t>5</t></is></c><c r="B28" s="48" t="inlineStr"><is><t>Garage house-to-garage: confirm 20-min fire rating still required under DOOR 4 spec</t></is></c></row><row r="29" ht="26" customHeight="1"><c r="A29" s="47" t="inlineStr"><is><t>6</t></is></c><c r="B29" s="48" t="inlineStr"><is><t>Panic room ballistic door: obtain separate spec/quote (Brown Safe or equiv) &#8211; NOT in TruStile order</t></is></c></row><row r="30" ht="26" customHeight="1"><c r="A30" s="47" t="inlineStr"><is><t>7</t></is></c><c r="B30" s="48" t="inlineStr"><is><t>Verify kerf placement on all fire-rated doors (TruStile warning noted on Line 4 of existing quote)</t></is></c></row><row r="31" ht="26" customHeight="1"><c r="A31" s="47" t="inlineStr"><is><t>8</t></is></c><c r="B31" s="48" t="inlineStr"><is><t>Lead time 7-8 weeks from confirmed PO &#8211; align order date with framing/finish milestone</t></is></c></row></sheetData><mergeCells count="14"><mergeCell ref="A2:L2"/><mergeCell ref="B26:L26"/><mergeCell ref="A21:H21"/><mergeCell ref="B30:L30"/><mergeCell ref="B29:L29"/><mergeCell ref="A1:L1"/><mergeCell ref="A23:L23"/><mergeCell ref="B24:L24"/><mergeCell ref="A13:L13"/><mergeCell ref="B25:L25"/><mergeCell ref="B28:L28"/><mergeCell ref="B31:L31"/><mergeCell ref="B27:L27"/><mergeCell ref="A4:L4"/></mergeCells><pageMargins left="0.75" right="0.75" top="1" bottom="1" header="0.5" footer="0.5"/><pageSetup orientation="landscape"/></worksheet>